ucbl_logger/__init__.py
ucbl_logger/core_logger.py
ucbl_logger/eks_logger.py
ucbl_logger/interfaces.py
ucbl_logger/logger.py
ucbl_logger/logger_factory.py
ucbl_logger/providers.py
ucbl_logger/risk_logger.py
ucbl_logger/task_logger.py
ucbl_logger/enhanced/README.md
ucbl_logger/enhanced/__init__.py
ucbl_logger/enhanced/config.py
ucbl_logger/enhanced/enhanced_eks_logger.py
ucbl_logger/enhanced/enhanced_eks_logger_impl.py
ucbl_logger/enhanced/factory.py
ucbl_logger/enhanced/initialization.py
ucbl_logger/enhanced/interfaces.py
ucbl_logger/enhanced/models.py
ucbl_logger/enhanced/tracing_integration.py
ucbl_logger/enhanced/buffering/__init__.py
ucbl_logger/enhanced/buffering/base.py
ucbl_logger/enhanced/buffering/enhanced_manager.py
ucbl_logger/enhanced/buffering/failure_handler.py
ucbl_logger/enhanced/buffering/interfaces.py
ucbl_logger/enhanced/buffering/models.py
ucbl_logger/enhanced/buffering/monitoring.py
ucbl_logger/enhanced/buffering/retry_manager.py
ucbl_logger/enhanced/cloudwatch/__init__.py
ucbl_logger/enhanced/cloudwatch/auto_config.py
ucbl_logger/enhanced/cloudwatch/batching.py
ucbl_logger/enhanced/cloudwatch/compression.py
ucbl_logger/enhanced/cloudwatch/error_handling.py
ucbl_logger/enhanced/cloudwatch/handler.py
ucbl_logger/enhanced/cloudwatch/interfaces.py
ucbl_logger/enhanced/cloudwatch/models.py
ucbl_logger/enhanced/cloudwatch/multi_destination.py
ucbl_logger/enhanced/cloudwatch/rate_limiter.py
ucbl_logger/enhanced/health/__init__.py
ucbl_logger/enhanced/health/base.py
ucbl_logger/enhanced/health/endpoint.py
ucbl_logger/enhanced/health/integration.py
ucbl_logger/enhanced/health/interfaces.py
ucbl_logger/enhanced/health/metrics.py
ucbl_logger/enhanced/health/models.py
ucbl_logger/enhanced/metadata/__init__.py
ucbl_logger/enhanced/metadata/base.py
ucbl_logger/enhanced/metadata/interfaces.py
ucbl_logger/enhanced/metadata/kubernetes_collector.py
ucbl_logger/enhanced/metadata/models.py
ucbl_logger/enhanced/performance/__init__.py
ucbl_logger-1.1.0.dist-info/METADATA
ucbl_logger-1.1.0.dist-info/WHEEL
ucbl_logger-1.1.0.dist-info/licenses/LICENSE
ucbl_logger-1.1.0.dist-info/RECORD
