Metadata-Version: 2.4
Name: ucbl-logger
Version: 1.1.0
Summary: A User-Centric Behaviour Log Markup Language Logger
Author-email: Evan Erwee <evan@erwee.com>
License-Expression: CC-BY-NC-ND-4.0
License-File: LICENSE
Classifier: Intended Audience :: Developers
Classifier: Intended Audience :: Information Technology
Classifier: License :: Other/Proprietary License
Classifier: Operating System :: OS Independent
Classifier: Programming Language :: Python :: 3
Classifier: Topic :: Software Development :: Libraries
Requires-Python: >=3.11
Requires-Dist: boto3>=1.26.0
Requires-Dist: kubernetes>=28.1.0
Requires-Dist: psutil>=5.8.0
Requires-Dist: pytz
Provides-Extra: eks
Requires-Dist: opentelemetry-api>=1.0.0; extra == 'eks'
Requires-Dist: prometheus-client>=0.14.0; extra == 'eks'
Provides-Extra: test
Requires-Dist: moto[ec2,eks]>=4.0.0; extra == 'test'
Requires-Dist: pytest-cov>=2.0; extra == 'test'
Requires-Dist: pytest-mock>=3.0; extra == 'test'
Requires-Dist: pytest>=6.0; extra == 'test'
